[
    {
        "jungle_id":23614,
        "level":"Advanced"
    },
    {
        "jungle_id":23594,
        "level":"Elementary/Pre-Intermediate"
    },
    {
        "jungle_id":23595,
        "level":"Intermediate"
    },
    {
        "jungle_id":23597,
        "level":"Advanced"
    },
    {
        "jungle_id":23598,
        "level":"Upper-Intermediate"
    },
    {
        "jungle_id":23599,
        "level":"Intermediate"
    },
    {
        "jungle_id":23600,
        "level":"Advanced"
    },
    {
        "jungle_id":23580,
        "level":"Upper-Intermediate"
    },
    {
        "jungle_id":23603,
        "level":"Upper-Intermediate"
    },
    {
        "jungle_id":23607,
        "level":"Elementary/Pre-Intermediate"
    },
    {
        "jungle_id":23608,
        "level":"Intermediate"
    },
    {
        "jungle_id":23611,
        "level":"Upper-Intermediate"
    },
    {
        "jungle_id":23593,
        "level":"Elementary/Pre-Intermediate"
    },
    {
        "jungle_id":23580,
        "level":"Upper-Intermediate"
    },
    {
        "jungle_id":23614,
        "level":"Advanced"
    },
    {
        "jungle_id":23583,
        "level":"Elementary/Pre-Intermediate"
    },
    {
        "jungle_id":23580,
        "level":"Intermediate"
    },
    {
        "jungle_id":23610,
        "level":"Intermediate"
    },
    {
        "jungle_id":23604,
        "level":"Elementary/Pre-Intermediate"
    },
    {
        "jungle_id":23587,
        "level":"Intermediate"
    },
    {
        "jungle_id":23592,
        "level":"Intermediate"
    },
    {
        "jungle_id":23606,
        "level":"Elementary/Pre-Intermediate"
    },
    {
        "jungle_id":23584,
        "level":"Intermediate"
    },
    {
        "jungle_id":23612,
        "level":"Upper-Intermediate"
    }
]