[
    {
        "jungle_id":30444,
        "level":"Upper-Intermediate"
    },
    {
        "jungle_id":30421,
        "level":"Upper-Intermediate"
    },
    {
        "jungle_id":30422,
        "level":"Elementary/Pre-Intermediate"
    },
    {
        "jungle_id":30435,
        "level":"Intermediate"
    },
    {
        "jungle_id":30418,
        "level":"Intermediate"
    },
    {
        "jungle_id":30433,
        "level":"Upper-Intermediate"
    },
    {
        "jungle_id":30416,
        "level":"Advanced"
    },
    {
        "jungle_id":30444,
        "level":"Advanced"
    },
    {
        "jungle_id":30420,
        "level":"Elementary/Pre-Intermediate"
    },
    {
        "jungle_id":30424,
        "level":"Upper-Intermediate"
    },
    {
        "jungle_id":30443,
        "level":"Upper-Intermediate"
    },
    {
        "jungle_id":30426,
        "level":"Intermediate"
    },
    {
        "jungle_id":30408,
        "level":"Intermediate"
    },
    {
        "jungle_id":30448,
        "level":"Upper-Intermediate"
    },
    {
        "jungle_id":30408,
        "level":"Intermediate"
    },
    {
        "jungle_id":30425,
        "level":"Upper-Intermediate"
    },
    {
        "jungle_id":30450,
        "level":"Intermediate"
    },
    {
        "jungle_id":30451,
        "level":"Advanced"
    }
]