[
    {
        "jungle_id":54725,
        "level":"Upper-Intermediate"
    },
    {
        "jungle_id":54730,
        "level":"Upper-Intermediate"
    },
    {
        "jungle_id":54732,
        "level":"Elementary/Pre-Intermediate"
    },
    {
        "jungle_id":54733,
        "level":"Upper-Intermediate"
    },
    {
        "jungle_id":54772,
        "level":"Intermediate"
    },
    {
        "jungle_id":54775,
        "level":"Upper-Intermediate"
    },
    {
        "jungle_id":54776,
        "level":"Elementary/Pre-Intermediate"
    },
    {
        "jungle_id":54734,
        "level":"Upper-Intermediate"
    },
    {
        "jungle_id":54735,
        "level":"Elementary/Pre-Intermediate"
    },
    {
        "jungle_id":54736,
        "level":"Intermediate"
    },
    {
        "jungle_id":54737,
        "level":"Intermediate"
    },
    {
        "jungle_id":54743,
        "level":"Elementary/Pre-Intermediate"
    },
    {
        "jungle_id":54744,
        "level":"Upper-Intermediate"
    },
    {
        "jungle_id":54746,
        "level":"Elementary/Pre-Intermediate"
    },
    {
        "jungle_id":54797,
        "level":"Upper-Intermediate"
    },
    {
        "jungle_id":54868,
        "level":"Upper-Intermediate"
    },
    {
        "jungle_id":54746,
        "level":"Elementary/Pre-Intermediate"
    },
    {
        "jungle_id":54748,
        "level":"Upper-Intermediate"
    },
    {
        "jungle_id":54749,
        "level":"Elementary/Pre-Intermediate"
    },
    {
        "jungle_id":54751,
        "level":"Elementary/Pre-Intermediate"
    },
    {
        "jungle_id":54753,
        "level":"Elementary/Pre-Intermediate"
    },
    {
        "jungle_id":54754,
        "level":"Upper-Intermediate"
    },
    {
        "jungle_id":54778,
        "level":"Advanced"
    },
    {
        "jungle_id":54729,
        "level":"Upper-Intermediate"
    },
    {
        "jungle_id":54754,
        "level":"Upper-Intermediate"
    },
    {
        "jungle_id":54760,
        "level":"Intermediate"
    },
    {
        "jungle_id":54806,
        "level":"Intermediate"
    },
    {
        "jungle_id":54868,
        "level":"Upper-Intermediate"
    },
    {
        "jungle_id":54754,
        "level":"Upper-Intermediate"
    },
    {
        "jungle_id":54755,
        "level":"Elementary/Pre-Intermediate"
    },
    {
        "jungle_id":54758,
        "level":"Advanced"
    },
    {
        "jungle_id":54729,
        "level":"Upper-Intermediate"
    },
    {
        "jungle_id":54832,
        "level":"Elementary/Pre-Intermediate"
    },
    {
        "jungle_id":54868,
        "level":"Advanced"
    },
    {
        "jungle_id":54759,
        "level":"Elementary/Pre-Intermediate"
    },
    {
        "jungle_id":54760,
        "level":"Upper-Intermediate"
    },
    {
        "jungle_id":54868,
        "level":"Upper-Intermediate"
    },
    {
        "jungle_id":54761,
        "level":"Upper-Intermediate"
    },
    {
        "jungle_id":54764,
        "level":"Upper-Intermediate"
    }
]