[
    {
        "jungle_id":64162,
        "level":"Upper-Intermediate"
    },
    {
        "jungle_id":64138,
        "level":"Elementary/Pre-Intermediate"
    },
    {
        "jungle_id":64183,
        "level":"Upper-Intermediate"
    },
    {
        "jungle_id":64185,
        "level":"Intermediate"
    },
    {
        "jungle_id":64162,
        "level":"Advanced"
    },
    {
        "jungle_id":64163,
        "level":"Intermediate"
    },
    {
        "jungle_id":64166,
        "level":"Intermediate"
    },
    {
        "jungle_id":64168,
        "level":"Upper-Intermediate"
    },
    {
        "jungle_id":64169,
        "level":"Elementary/Pre-Intermediate"
    },
    {
        "jungle_id":64171,
        "level":"Intermediate"
    },
    {
        "jungle_id":64173,
        "level":"Upper-Intermediate"
    },
    {
        "jungle_id":64185,
        "level":"Upper-Intermediate"
    },
    {
        "jungle_id":64173,
        "level":"Upper-Intermediate"
    },
    {
        "jungle_id":64181,
        "level":"Advanced"
    },
    {
        "jungle_id":64182,
        "level":"Upper-Intermediate"
    },
    {
        "jungle_id":64173,
        "level":"Upper-Intermediate"
    },
    {
        "jungle_id":64174,
        "level":"Advanced"
    },
    {
        "jungle_id":64176,
        "level":"Upper-Intermediate"
    },
    {
        "jungle_id":64178,
        "level":"Upper-Intermediate"
    },
    {
        "jungle_id":64182,
        "level":"Upper-Intermediate"
    }
]