[
    {
        "level":"Advanced",
        "jungle_id":6086
    },
    {
        "level":"Beginner",
        "jungle_id":6049
    },
    {
        "level":"Elementary/Pre-Intermediate",
        "jungle_id":6081
    },
    {
        "level":"Advanced",
        "jungle_id":6082
    },
    {
        "level":"Upper-Intermediate",
        "jungle_id":6062
    },
    {
        "level":"Upper-Intermediate",
        "jungle_id":6050
    },
    {
        "level":"Elementary/Pre-Intermediate",
        "jungle_id":6083
    },
    {
        "level":"Advanced",
        "jungle_id":6070
    },
    {
        "level":"Advanced",
        "jungle_id":6653
    },
    {
        "level":"Upper-Intermediate",
        "jungle_id":6070
    },
    {
        "level":"Upper-Intermediate",
        "jungle_id":6069
    }
]