[
    {
        "jungle_id":9662,
        "level":"Advanced"
    },
    {
        "jungle_id":9296,
        "level":"Intermediate"
    },
    {
        "jungle_id":9303,
        "level":"Beginner"
    },
    {
        "jungle_id":9664,
        "level":"Upper-Intermediate"
    },
    {
        "jungle_id":9250,
        "level":"Elementary/Pre-Intermediate"
    },
    {
        "jungle_id":9289,
        "level":"Upper-Intermediate"
    },
    {
        "jungle_id":9267,
        "level":"Intermediate"
    },
    {
        "jungle_id":9295,
        "level":"Intermediate"
    },
    {
        "jungle_id":9312,
        "level":"Intermediate"
    },
    {
        "jungle_id":9662,
        "level":"Advanced"
    },
    {
        "jungle_id":9252,
        "level":"Upper-Intermediate"
    },
    {
        "jungle_id":9664,
        "level":"Upper-Intermediate"
    },
    {
        "jungle_id":9280,
        "level":"Elementary/Pre-Intermediate"
    },
    {
        "jungle_id":9228,
        "level":"Intermediate"
    },
    {
        "jungle_id":9300,
        "level":"Upper-Intermediate"
    },
    {
        "jungle_id":9278,
        "level":"Intermediate"
    },
    {
        "jungle_id":9231,
        "level":"Upper-Intermediate"
    },
    {
        "jungle_id":9288,
        "level":"Upper-Intermediate"
    },
    {
        "jungle_id":9311,
        "level":"Upper-Intermediate"
    },
    {
        "jungle_id":9662,
        "level":"Advanced"
    },
    {
        "jungle_id":9223,
        "level":"Advanced"
    },
    {
        "jungle_id":9234,
        "level":"Intermediate"
    },
    {
        "jungle_id":9664,
        "level":"Upper-Intermediate"
    },
    {
        "jungle_id":9234,
        "level":"Intermediate"
    },
    {
        "jungle_id":9219,
        "level":"Intermediate"
    },
    {
        "jungle_id":9214,
        "level":"Advanced"
    },
    {
        "jungle_id":9213,
        "level":"Intermediate"
    },
    {
        "jungle_id":9662,
        "level":"Advanced"
    },
    {
        "jungle_id":9211,
        "level":"Elementary/Pre-Intermediate"
    },
    {
        "jungle_id":9254,
        "level":"Intermediate"
    },
    {
        "jungle_id":9664,
        "level":"Upper-Intermediate"
    },
    {
        "jungle_id":9299,
        "level":"Elementary/Pre-Intermediate"
    },
    {
        "jungle_id":9229,
        "level":"Intermediate"
    },
    {
        "jungle_id":9265,
        "level":"Upper-Intermediate"
    },
    {
        "jungle_id":9287,
        "level":"Advanced"
    },
    {
        "jungle_id":9263,
        "level":"Elementary/Pre-Intermediate"
    },
    {
        "jungle_id":9308,
        "level":"Upper-Intermediate"
    },
    {
        "jungle_id":9662,
        "level":"Advanced"
    },
    {
        "jungle_id":9319,
        "level":"Upper-Intermediate"
    },
    {
        "jungle_id":9664,
        "level":"Upper-Intermediate"
    },
    {
        "jungle_id":9308,
        "level":"Advanced"
    },
    {
        "jungle_id":9309,
        "level":"Intermediate"
    },
    {
        "jungle_id":9310,
        "level":"Intermediate"
    },
    {
        "jungle_id":9317,
        "level":"Intermediate"
    }
]