[
    {
        "jungle_id":17106,
        "level":"Upper-Intermediate"
    },
    {
        "jungle_id":17107,
        "level":"Upper-Intermediate"
    },
    {
        "jungle_id":17114,
        "level":"Advanced"
    },
    {
        "jungle_id":17671,
        "level":"Intermediate"
    },
    {
        "jungle_id":17014,
        "level":"Upper-Intermediate"
    },
    {
        "jungle_id":17253,
        "level":"Upper-Intermediate"
    },
    {
        "jungle_id":17118,
        "level":"Intermediate"
    },
    {
        "jungle_id":16997,
        "level":"Elementary/Pre-Intermediate"
    },
    {
        "jungle_id":17035,
        "level":"Intermediate"
    },
    {
        "jungle_id":17040,
        "level":"Intermediate"
    },
    {
        "jungle_id":17671,
        "level":"Intermediate"
    },
    {
        "jungle_id":17049,
        "level":"Elementary/Pre-Intermediate"
    },
    {
        "jungle_id":17010,
        "level":"Upper-Intermediate"
    },
    {
        "jungle_id":17011,
        "level":"Upper-Intermediate"
    },
    {
        "jungle_id":17175,
        "level":"Upper-Intermediate"
    },
    {
        "jungle_id":17671,
        "level":"Intermediate"
    },
    {
        "jungle_id":17015,
        "level":"Upper-Intermediate"
    },
    {
        "jungle_id":17093,
        "level":"Advanced"
    },
    {
        "jungle_id":17253,
        "level":"Upper-Intermediate"
    },
    {
        "jungle_id":17104,
        "level":"Intermediate"
    },
    {
        "jungle_id":17070,
        "level":"Intermediate"
    },
    {
        "jungle_id":17098,
        "level":"Intermediate"
    },
    {
        "jungle_id":17034,
        "level":"Intermediate"
    },
    {
        "jungle_id":17116,
        "level":"Intermediate"
    },
    {
        "jungle_id":17671,
        "level":"Intermediate"
    },
    {
        "jungle_id":17064,
        "level":"Upper-Intermediate"
    },
    {
        "jungle_id":17086,
        "level":"Upper-Intermediate"
    },
    {
        "jungle_id":17253,
        "level":"Intermediate"
    },
    {
        "jungle_id":17103,
        "level":"Upper-Intermediate"
    },
    {
        "jungle_id":17073,
        "level":"Advanced"
    },
    {
        "jungle_id":17053,
        "level":"Intermediate"
    },
    {
        "jungle_id":17090,
        "level":"Elementary/Pre-Intermediate"
    },
    {
        "jungle_id":17320,
        "level":"Elementary/Pre-Intermediate"
    },
    {
        "jungle_id":17322,
        "level":"Upper-Intermediate"
    },
    {
        "jungle_id":17042,
        "level":"Intermediate"
    },
    {
        "jungle_id":17082,
        "level":"Advanced"
    },
    {
        "jungle_id":17012,
        "level":"Intermediate"
    },
    {
        "jungle_id":17080,
        "level":"Elementary/Pre-Intermediate"
    },
    {
        "jungle_id":17253,
        "level":"Upper-Intermediate"
    },
    {
        "jungle_id":17045,
        "level":"Intermediate"
    },
    {
        "jungle_id":17006,
        "level":"Upper-Intermediate"
    },
    {
        "jungle_id":17066,
        "level":"Elementary/Pre-Intermediate"
    },
    {
        "jungle_id":17139,
        "level":"Elementary/Pre-Intermediate"
    },
    {
        "jungle_id":17322,
        "level":"Intermediate"
    },
    {
        "jungle_id":17671,
        "level":"Upper-Intermediate"
    },
    {
        "jungle_id":17089,
        "level":"Advanced"
    },
    {
        "jungle_id":17017,
        "level":"Elementary/Pre-Intermediate"
    },
    {
        "jungle_id":17031,
        "level":"Advanced"
    },
    {
        "jungle_id":17044,
        "level":"Elementary/Pre-Intermediate"
    },
    {
        "jungle_id":17115,
        "level":"Elementary/Pre-Intermediate"
    },
    {
        "jungle_id":17052,
        "level":"Intermediate"
    },
    {
        "jungle_id":17201,
        "level":"Advanced"
    },
    {
        "jungle_id":17671,
        "level":"Intermediate"
    },
    {
        "jungle_id":17052,
        "level":"Intermediate"
    },
    {
        "jungle_id":17058,
        "level":"Intermediate"
    },
    {
        "jungle_id":17020,
        "level":"Elementary/Pre-Intermediate"
    },
    {
        "jungle_id":17046,
        "level":"Intermediate"
    },
    {
        "jungle_id":17113,
        "level":"Advanced"
    }
]