[
    {
        "jungle_id":311770,
        "level":"Upper-Intermediate"
    },
    {
        "jungle_id":311771,
        "level":"Advanced"
    },
    {
        "jungle_id":311772,
        "level":"Upper-Intermediate"
    },
    {
        "jungle_id":311773,
        "level":"Upper-Intermediate"
    },
    {
        "jungle_id":311774,
        "level":"Upper-Intermediate"
    },
    {
        "jungle_id":311775,
        "level":"Elementary/Pre-Intermediate"
    },
    {
        "jungle_id":311776,
        "level":"Upper-Intermediate"
    },
    {
        "jungle_id":311779,
        "level":"Upper-Intermediate"
    },
    {
        "jungle_id":311780,
        "level":"Upper-Intermediate"
    },
    {
        "jungle_id":311781,
        "level":"Upper-Intermediate"
    },
    {
        "jungle_id":311782,
        "level":"Advanced"
    },
    {
        "jungle_id":311783,
        "level":"Upper-Intermediate"
    },
    {
        "jungle_id":311784,
        "level":"Upper-Intermediate"
    },
    {
        "jungle_id":311785,
        "level":"Upper-Intermediate"
    },
    {
        "jungle_id":311786,
        "level":"Upper-Intermediate"
    },
    {
        "jungle_id":311787,
        "level":"Upper-Intermediate"
    },
    {
        "jungle_id":311788,
        "level":"Upper-Intermediate"
    },
    {
        "jungle_id":311789,
        "level":"Upper-Intermediate"
    },
    {
        "jungle_id":311790,
        "level":"Upper-Intermediate"
    },
    {
        "jungle_id":311791,
        "level":"Advanced"
    },
    {
        "jungle_id":311792,
        "level":"Upper-Intermediate"
    },
    {
        "jungle_id":311793,
        "level":"Upper-Intermediate"
    },
    {
        "jungle_id":311794,
        "level":"Upper-Intermediate"
    },
    {
        "jungle_id":311795,
        "level":"Upper-Intermediate"
    },
    {
        "jungle_id":311796,
        "level":"Upper-Intermediate"
    },
    {
        "jungle_id":311797,
        "level":"Upper-Intermediate"
    },
    {
        "jungle_id":311798,
        "level":"Upper-Intermediate"
    },
    {
        "jungle_id":311799,
        "level":"Advanced"
    },
    {
        "jungle_id":311800,
        "level":"Upper-Intermediate"
    },
    {
        "jungle_id":311801,
        "level":"Upper-Intermediate"
    },
    {
        "jungle_id":311802,
        "level":"Elementary/Pre-Intermediate"
    },
    {
        "jungle_id":311804,
        "level":"Intermediate"
    },
    {
        "jungle_id":311805,
        "level":"Advanced"
    },
    {
        "jungle_id":311806,
        "level":"Elementary/Pre-Intermediate"
    },
    {
        "jungle_id":311807,
        "level":"Beginner"
    },
    {
        "jungle_id":311808,
        "level":"Intermediate"
    },
    {
        "jungle_id":311809,
        "level":"Upper-Intermediate"
    },
    {
        "jungle_id":311810,
        "level":"Elementary/Pre-Intermediate"
    },
    {
        "jungle_id":311811,
        "level":"Advanced"
    },
    {
        "jungle_id":311812,
        "level":"Intermediate"
    },
    {
        "jungle_id":311813,
        "level":"Elementary/Pre-Intermediate"
    },
    {
        "jungle_id":311814,
        "level":"Elementary/Pre-Intermediate"
    }
]