[
    {
        "jungle_id":358443,
        "level":"Intermediate"
    },
    {
        "jungle_id":358444,
        "level":"Upper-Intermediate"
    },
    {
        "jungle_id":358446,
        "level":"Intermediate"
    },
    {
        "jungle_id":358447,
        "level":"Intermediate"
    },
    {
        "jungle_id":358448,
        "level":"Intermediate"
    },
    {
        "jungle_id":358449,
        "level":"Elementary/Pre-Intermediate"
    },
    {
        "jungle_id":358450,
        "level":"Upper-Intermediate"
    },
    {
        "jungle_id":358451,
        "level":"Intermediate"
    },
    {
        "jungle_id":358452,
        "level":"Intermediate"
    },
    {
        "jungle_id":358453,
        "level":"Intermediate"
    },
    {
        "jungle_id":358454,
        "level":"Upper-Intermediate"
    },
    {
        "jungle_id":358455,
        "level":"Intermediate"
    },
    {
        "jungle_id":358456,
        "level":"Intermediate"
    },
    {
        "jungle_id":358457,
        "level":"Upper-Intermediate"
    },
    {
        "jungle_id":358459,
        "level":"Elementary/Pre-Intermediate"
    },
    {
        "jungle_id":358460,
        "level":"Upper-Intermediate"
    },
    {
        "jungle_id":358461,
        "level":"Elementary/Pre-Intermediate"
    },
    {
        "jungle_id":358462,
        "level":"Upper-Intermediate"
    },
    {
        "jungle_id":358464,
        "level":"Intermediate"
    },
    {
        "jungle_id":358465,
        "level":"Intermediate"
    },
    {
        "jungle_id":358468,
        "level":"Advanced"
    },
    {
        "jungle_id":358470,
        "level":"Upper-Intermediate"
    },
    {
        "jungle_id":358471,
        "level":"Upper-Intermediate"
    },
    {
        "jungle_id":358473,
        "level":"Upper-Intermediate"
    },
    {
        "jungle_id":358475,
        "level":"Advanced"
    },
    {
        "jungle_id":358479,
        "level":"Intermediate"
    },
    {
        "jungle_id":358482,
        "level":"Intermediate"
    },
    {
        "jungle_id":358484,
        "level":"Intermediate"
    },
    {
        "jungle_id":358489,
        "level":"Text seems to be empty"
    },
    {
        "jungle_id":358490,
        "level":"Intermediate"
    },
    {
        "jungle_id":358495,
        "level":"Upper-Intermediate"
    },
    {
        "jungle_id":358496,
        "level":"Upper-Intermediate"
    },
    {
        "jungle_id":358497,
        "level":"Elementary/Pre-Intermediate"
    },
    {
        "jungle_id":358499,
        "level":"Upper-Intermediate"
    },
    {
        "jungle_id":358500,
        "level":"Intermediate"
    },
    {
        "jungle_id":358501,
        "level":"Elementary/Pre-Intermediate"
    },
    {
        "jungle_id":358503,
        "level":"Advanced"
    },
    {
        "jungle_id":358504,
        "level":"Intermediate"
    },
    {
        "jungle_id":358505,
        "level":"Elementary/Pre-Intermediate"
    },
    {
        "jungle_id":358507,
        "level":"Intermediate"
    },
    {
        "jungle_id":358510,
        "level":"Upper-Intermediate"
    },
    {
        "jungle_id":358511,
        "level":"Advanced"
    },
    {
        "jungle_id":358513,
        "level":"Intermediate"
    },
    {
        "jungle_id":358515,
        "level":"Upper-Intermediate"
    },
    {
        "jungle_id":358516,
        "level":"Advanced"
    },
    {
        "jungle_id":358517,
        "level":"Elementary/Pre-Intermediate"
    },
    {
        "jungle_id":358519,
        "level":"Upper-Intermediate"
    },
    {
        "jungle_id":358521,
        "level":"Upper-Intermediate"
    },
    {
        "jungle_id":358522,
        "level":"Elementary/Pre-Intermediate"
    },
    {
        "jungle_id":358524,
        "level":"Upper-Intermediate"
    },
    {
        "jungle_id":358525,
        "level":"Upper-Intermediate"
    },
    {
        "jungle_id":358529,
        "level":"Intermediate"
    },
    {
        "jungle_id":358531,
        "level":"Upper-Intermediate"
    },
    {
        "jungle_id":358532,
        "level":"Intermediate"
    },
    {
        "jungle_id":358534,
        "level":"Intermediate"
    },
    {
        "jungle_id":358536,
        "level":"Intermediate"
    },
    {
        "jungle_id":358537,
        "level":"Upper-Intermediate"
    },
    {
        "jungle_id":358538,
        "level":"Upper-Intermediate"
    },
    {
        "jungle_id":358539,
        "level":"Advanced"
    },
    {
        "jungle_id":358540,
        "level":"Upper-Intermediate"
    },
    {
        "jungle_id":358541,
        "level":"Upper-Intermediate"
    },
    {
        "jungle_id":358543,
        "level":"Upper-Intermediate"
    },
    {
        "jungle_id":358544,
        "level":"Advanced"
    },
    {
        "jungle_id":358547,
        "level":"Upper-Intermediate"
    },
    {
        "jungle_id":358548,
        "level":"Upper-Intermediate"
    },
    {
        "jungle_id":358549,
        "level":"Elementary/Pre-Intermediate"
    },
    {
        "jungle_id":358550,
        "level":"Intermediate"
    },
    {
        "jungle_id":358551,
        "level":"Advanced"
    }
]