[
    {
        "jungle_id":364174,
        "level":"Upper-Intermediate"
    },
    {
        "jungle_id":364175,
        "level":"Advanced"
    },
    {
        "jungle_id":364177,
        "level":"Intermediate"
    },
    {
        "jungle_id":364179,
        "level":"Upper-Intermediate"
    },
    {
        "jungle_id":364184,
        "level":"Upper-Intermediate"
    },
    {
        "jungle_id":364185,
        "level":"Upper-Intermediate"
    },
    {
        "jungle_id":364186,
        "level":"Intermediate"
    },
    {
        "jungle_id":364189,
        "level":"Beginner"
    },
    {
        "jungle_id":364192,
        "level":"Upper-Intermediate"
    },
    {
        "jungle_id":364193,
        "level":"Advanced"
    },
    {
        "jungle_id":364194,
        "level":"Advanced"
    },
    {
        "jungle_id":364195,
        "level":"Upper-Intermediate"
    },
    {
        "jungle_id":364198,
        "level":"Upper-Intermediate"
    },
    {
        "jungle_id":364199,
        "level":"Upper-Intermediate"
    },
    {
        "jungle_id":364200,
        "level":"Intermediate"
    },
    {
        "jungle_id":364202,
        "level":"Upper-Intermediate"
    },
    {
        "jungle_id":364203,
        "level":"Intermediate"
    },
    {
        "jungle_id":364204,
        "level":"Intermediate"
    },
    {
        "jungle_id":364206,
        "level":"Upper-Intermediate"
    },
    {
        "jungle_id":364207,
        "level":"Upper-Intermediate"
    },
    {
        "jungle_id":364212,
        "level":"Upper-Intermediate"
    },
    {
        "jungle_id":364214,
        "level":"Intermediate"
    },
    {
        "jungle_id":364215,
        "level":"Upper-Intermediate"
    },
    {
        "jungle_id":364216,
        "level":"Beginner"
    },
    {
        "jungle_id":364218,
        "level":"Upper-Intermediate"
    },
    {
        "jungle_id":364219,
        "level":"Intermediate"
    },
    {
        "jungle_id":364220,
        "level":"Upper-Intermediate"
    },
    {
        "jungle_id":364227,
        "level":"Intermediate"
    },
    {
        "jungle_id":364229,
        "level":"Intermediate"
    },
    {
        "jungle_id":364230,
        "level":"Elementary/Pre-Intermediate"
    },
    {
        "jungle_id":364231,
        "level":"Upper-Intermediate"
    },
    {
        "jungle_id":364234,
        "level":"Intermediate"
    },
    {
        "jungle_id":364235,
        "level":"Upper-Intermediate"
    }
]