[
    {
        "jungle_id":369662,
        "level":"Elementary/Pre-Intermediate"
    },
    {
        "jungle_id":369663,
        "level":"Upper-Intermediate"
    },
    {
        "jungle_id":369666,
        "level":"Upper-Intermediate"
    },
    {
        "jungle_id":369667,
        "level":"Upper-Intermediate"
    },
    {
        "jungle_id":369670,
        "level":"Upper-Intermediate"
    },
    {
        "jungle_id":369672,
        "level":"Text seems to be empty"
    },
    {
        "jungle_id":369673,
        "level":"Advanced"
    },
    {
        "jungle_id":369674,
        "level":"Advanced"
    }
]