[
    {
        "jungle_id":410557,
        "level":"Intermediate"
    },
    {
        "jungle_id":410558,
        "level":"Intermediate"
    },
    {
        "jungle_id":410559,
        "level":"Upper-Intermediate"
    },
    {
        "jungle_id":410560,
        "level":"Upper-Intermediate"
    },
    {
        "jungle_id":410561,
        "level":"Elementary/Pre-Intermediate"
    },
    {
        "jungle_id":410562,
        "level":"Upper-Intermediate"
    },
    {
        "jungle_id":410564,
        "level":"Upper-Intermediate"
    },
    {
        "jungle_id":410565,
        "level":"Intermediate"
    },
    {
        "jungle_id":410567,
        "level":"Upper-Intermediate"
    },
    {
        "jungle_id":410568,
        "level":"Elementary/Pre-Intermediate"
    },
    {
        "jungle_id":410569,
        "level":"Intermediate"
    },
    {
        "jungle_id":410570,
        "level":"Intermediate"
    },
    {
        "jungle_id":410571,
        "level":"Upper-Intermediate"
    },
    {
        "jungle_id":410572,
        "level":"Upper-Intermediate"
    },
    {
        "jungle_id":410573,
        "level":"Intermediate"
    },
    {
        "jungle_id":410574,
        "level":"Advanced"
    },
    {
        "jungle_id":410575,
        "level":"Beginner"
    },
    {
        "jungle_id":410579,
        "level":"Upper-Intermediate"
    },
    {
        "jungle_id":410580,
        "level":"Intermediate"
    },
    {
        "jungle_id":410581,
        "level":"Advanced"
    },
    {
        "jungle_id":410583,
        "level":"Upper-Intermediate"
    },
    {
        "jungle_id":410585,
        "level":"Intermediate"
    },
    {
        "jungle_id":410586,
        "level":"Beginner"
    },
    {
        "jungle_id":410587,
        "level":"Intermediate"
    },
    {
        "jungle_id":410589,
        "level":"Intermediate"
    },
    {
        "jungle_id":410591,
        "level":"Upper-Intermediate"
    },
    {
        "jungle_id":410592,
        "level":"Beginner"
    },
    {
        "jungle_id":410593,
        "level":"Upper-Intermediate"
    },
    {
        "jungle_id":410596,
        "level":"Upper-Intermediate"
    },
    {
        "jungle_id":410597,
        "level":"Elementary/Pre-Intermediate"
    },
    {
        "jungle_id":410598,
        "level":"Intermediate"
    },
    {
        "jungle_id":410599,
        "level":"Elementary/Pre-Intermediate"
    },
    {
        "jungle_id":410600,
        "level":"Upper-Intermediate"
    },
    {
        "jungle_id":410601,
        "level":"Upper-Intermediate"
    },
    {
        "jungle_id":410602,
        "level":"Advanced"
    },
    {
        "jungle_id":410603,
        "level":"Upper-Intermediate"
    },
    {
        "jungle_id":410604,
        "level":"Elementary/Pre-Intermediate"
    },
    {
        "jungle_id":410606,
        "level":"Intermediate"
    },
    {
        "jungle_id":410607,
        "level":"Upper-Intermediate"
    },
    {
        "jungle_id":410608,
        "level":"Upper-Intermediate"
    },
    {
        "jungle_id":410609,
        "level":"Upper-Intermediate"
    },
    {
        "jungle_id":410610,
        "level":"Upper-Intermediate"
    },
    {
        "jungle_id":410611,
        "level":"Upper-Intermediate"
    },
    {
        "jungle_id":410613,
        "level":"Upper-Intermediate"
    },
    {
        "jungle_id":410614,
        "level":"Upper-Intermediate"
    },
    {
        "jungle_id":410615,
        "level":"Upper-Intermediate"
    },
    {
        "jungle_id":410616,
        "level":"Upper-Intermediate"
    },
    {
        "jungle_id":410617,
        "level":"Upper-Intermediate"
    },
    {
        "jungle_id":410619,
        "level":"Upper-Intermediate"
    },
    {
        "jungle_id":410623,
        "level":"Elementary/Pre-Intermediate"
    },
    {
        "jungle_id":410626,
        "level":"Upper-Intermediate"
    },
    {
        "jungle_id":410627,
        "level":"Upper-Intermediate"
    },
    {
        "jungle_id":410628,
        "level":"Upper-Intermediate"
    },
    {
        "jungle_id":410629,
        "level":"Advanced"
    },
    {
        "jungle_id":410630,
        "level":"Upper-Intermediate"
    },
    {
        "jungle_id":410632,
        "level":"Upper-Intermediate"
    },
    {
        "jungle_id":410633,
        "level":"Advanced"
    },
    {
        "jungle_id":410634,
        "level":"Elementary/Pre-Intermediate"
    },
    {
        "jungle_id":410635,
        "level":"Intermediate"
    },
    {
        "jungle_id":410639,
        "level":"Elementary/Pre-Intermediate"
    },
    {
        "jungle_id":410640,
        "level":"Intermediate"
    },
    {
        "jungle_id":410642,
        "level":"Upper-Intermediate"
    },
    {
        "jungle_id":410644,
        "level":"Upper-Intermediate"
    },
    {
        "jungle_id":410646,
        "level":"Elementary/Pre-Intermediate"
    },
    {
        "jungle_id":410649,
        "level":"Elementary/Pre-Intermediate"
    },
    {
        "jungle_id":410651,
        "level":"Text seems to be empty"
    },
    {
        "jungle_id":410652,
        "level":"Advanced"
    },
    {
        "jungle_id":410653,
        "level":"Intermediate"
    },
    {
        "jungle_id":410654,
        "level":"Advanced"
    },
    {
        "jungle_id":410658,
        "level":"Intermediate"
    },
    {
        "jungle_id":410659,
        "level":"Elementary/Pre-Intermediate"
    },
    {
        "jungle_id":410660,
        "level":"Intermediate"
    },
    {
        "jungle_id":410661,
        "level":"Elementary/Pre-Intermediate"
    },
    {
        "jungle_id":410662,
        "level":"Upper-Intermediate"
    },
    {
        "jungle_id":410663,
        "level":"Intermediate"
    },
    {
        "jungle_id":410669,
        "level":"Elementary/Pre-Intermediate"
    }
]