[
    {
        "jungle_id":412630,
        "level":"Advanced"
    },
    {
        "jungle_id":412631,
        "level":"Upper-Intermediate"
    },
    {
        "jungle_id":412632,
        "level":"Advanced"
    },
    {
        "jungle_id":412633,
        "level":"Elementary/Pre-Intermediate"
    },
    {
        "jungle_id":412634,
        "level":"Upper-Intermediate"
    },
    {
        "jungle_id":412635,
        "level":"Upper-Intermediate"
    },
    {
        "jungle_id":412636,
        "level":"Intermediate"
    },
    {
        "jungle_id":412637,
        "level":"Intermediate"
    },
    {
        "jungle_id":412638,
        "level":"Elementary/Pre-Intermediate"
    },
    {
        "jungle_id":412639,
        "level":"Advanced"
    },
    {
        "jungle_id":412640,
        "level":"Intermediate"
    },
    {
        "jungle_id":412642,
        "level":"Upper-Intermediate"
    },
    {
        "jungle_id":412643,
        "level":"Intermediate"
    },
    {
        "jungle_id":412644,
        "level":"Upper-Intermediate"
    },
    {
        "jungle_id":412645,
        "level":"Advanced"
    },
    {
        "jungle_id":412647,
        "level":"Upper-Intermediate"
    },
    {
        "jungle_id":412648,
        "level":"Upper-Intermediate"
    },
    {
        "jungle_id":412650,
        "level":"Upper-Intermediate"
    },
    {
        "jungle_id":412651,
        "level":"Intermediate"
    },
    {
        "jungle_id":412652,
        "level":"Upper-Intermediate"
    },
    {
        "jungle_id":412653,
        "level":"Beginner"
    },
    {
        "jungle_id":412659,
        "level":"Beginner"
    },
    {
        "jungle_id":412662,
        "level":"Upper-Intermediate"
    },
    {
        "jungle_id":412664,
        "level":"Advanced"
    },
    {
        "jungle_id":412665,
        "level":"Upper-Intermediate"
    },
    {
        "jungle_id":412666,
        "level":"Upper-Intermediate"
    },
    {
        "jungle_id":412668,
        "level":"Upper-Intermediate"
    },
    {
        "jungle_id":412669,
        "level":"Intermediate"
    },
    {
        "jungle_id":412670,
        "level":"Intermediate"
    },
    {
        "jungle_id":412673,
        "level":"Text seems to be empty"
    },
    {
        "jungle_id":412677,
        "level":"Upper-Intermediate"
    },
    {
        "jungle_id":412678,
        "level":"Elementary/Pre-Intermediate"
    },
    {
        "jungle_id":412679,
        "level":"Intermediate"
    },
    {
        "jungle_id":412680,
        "level":"Upper-Intermediate"
    },
    {
        "jungle_id":412683,
        "level":"Upper-Intermediate"
    },
    {
        "jungle_id":412685,
        "level":"Upper-Intermediate"
    },
    {
        "jungle_id":412691,
        "level":"Upper-Intermediate"
    },
    {
        "jungle_id":412692,
        "level":"Upper-Intermediate"
    },
    {
        "jungle_id":412693,
        "level":"Advanced"
    },
    {
        "jungle_id":412694,
        "level":"Advanced"
    },
    {
        "jungle_id":412695,
        "level":"Intermediate"
    },
    {
        "jungle_id":412696,
        "level":"Upper-Intermediate"
    },
    {
        "jungle_id":412699,
        "level":"Intermediate"
    },
    {
        "jungle_id":412701,
        "level":"Advanced"
    },
    {
        "jungle_id":412702,
        "level":"Upper-Intermediate"
    },
    {
        "jungle_id":412703,
        "level":"Upper-Intermediate"
    },
    {
        "jungle_id":412705,
        "level":"Upper-Intermediate"
    },
    {
        "jungle_id":412712,
        "level":"Upper-Intermediate"
    },
    {
        "jungle_id":412714,
        "level":"Upper-Intermediate"
    },
    {
        "jungle_id":412715,
        "level":"Upper-Intermediate"
    },
    {
        "jungle_id":412716,
        "level":"Upper-Intermediate"
    },
    {
        "jungle_id":412717,
        "level":"Upper-Intermediate"
    },
    {
        "jungle_id":412718,
        "level":"Advanced"
    },
    {
        "jungle_id":412719,
        "level":"Upper-Intermediate"
    },
    {
        "jungle_id":412724,
        "level":"Elementary/Pre-Intermediate"
    },
    {
        "jungle_id":412725,
        "level":"Upper-Intermediate"
    },
    {
        "jungle_id":412726,
        "level":"Upper-Intermediate"
    },
    {
        "jungle_id":412727,
        "level":"Elementary/Pre-Intermediate"
    },
    {
        "jungle_id":412728,
        "level":"Upper-Intermediate"
    },
    {
        "jungle_id":412729,
        "level":"Upper-Intermediate"
    },
    {
        "jungle_id":412732,
        "level":"Upper-Intermediate"
    },
    {
        "jungle_id":412735,
        "level":"Intermediate"
    },
    {
        "jungle_id":412736,
        "level":"Intermediate"
    },
    {
        "jungle_id":412737,
        "level":"Upper-Intermediate"
    },
    {
        "jungle_id":412738,
        "level":"Intermediate"
    },
    {
        "jungle_id":412740,
        "level":"Upper-Intermediate"
    },
    {
        "jungle_id":412744,
        "level":"Advanced"
    },
    {
        "jungle_id":412752,
        "level":"Intermediate"
    },
    {
        "jungle_id":412754,
        "level":"Intermediate"
    },
    {
        "jungle_id":412769,
        "level":"Beginner"
    },
    {
        "jungle_id":412785,
        "level":"Upper-Intermediate"
    },
    {
        "jungle_id":412786,
        "level":"Upper-Intermediate"
    }
]