[
    {
        "jungle_id":431454,
        "level":"Upper-Intermediate"
    },
    {
        "jungle_id":431456,
        "level":"Intermediate"
    },
    {
        "jungle_id":431459,
        "level":"Upper-Intermediate"
    },
    {
        "jungle_id":431460,
        "level":"Intermediate"
    },
    {
        "jungle_id":431462,
        "level":"Elementary/Pre-Intermediate"
    },
    {
        "jungle_id":431464,
        "level":"Upper-Intermediate"
    },
    {
        "jungle_id":431465,
        "level":"Upper-Intermediate"
    },
    {
        "jungle_id":431466,
        "level":"Upper-Intermediate"
    },
    {
        "jungle_id":431467,
        "level":"Intermediate"
    },
    {
        "jungle_id":431468,
        "level":"Upper-Intermediate"
    },
    {
        "jungle_id":431469,
        "level":"Elementary/Pre-Intermediate"
    },
    {
        "jungle_id":431470,
        "level":"Upper-Intermediate"
    },
    {
        "jungle_id":431471,
        "level":"Advanced"
    },
    {
        "jungle_id":431472,
        "level":"Intermediate"
    },
    {
        "jungle_id":431473,
        "level":"Upper-Intermediate"
    },
    {
        "jungle_id":431475,
        "level":"Elementary/Pre-Intermediate"
    },
    {
        "jungle_id":431476,
        "level":"Upper-Intermediate"
    },
    {
        "jungle_id":431479,
        "level":"Upper-Intermediate"
    },
    {
        "jungle_id":431480,
        "level":"Elementary/Pre-Intermediate"
    },
    {
        "jungle_id":431482,
        "level":"Upper-Intermediate"
    },
    {
        "jungle_id":431483,
        "level":"Intermediate"
    },
    {
        "jungle_id":431484,
        "level":"Upper-Intermediate"
    },
    {
        "jungle_id":431485,
        "level":"Advanced"
    },
    {
        "jungle_id":431486,
        "level":"Beginner"
    },
    {
        "jungle_id":431487,
        "level":"Upper-Intermediate"
    },
    {
        "jungle_id":431489,
        "level":"Advanced"
    },
    {
        "jungle_id":431492,
        "level":"Intermediate"
    },
    {
        "jungle_id":431495,
        "level":"Upper-Intermediate"
    },
    {
        "jungle_id":431496,
        "level":"Intermediate"
    },
    {
        "jungle_id":431498,
        "level":"Advanced"
    },
    {
        "jungle_id":431499,
        "level":"Upper-Intermediate"
    },
    {
        "jungle_id":431501,
        "level":"Elementary/Pre-Intermediate"
    },
    {
        "jungle_id":431504,
        "level":"Upper-Intermediate"
    },
    {
        "jungle_id":431505,
        "level":"Upper-Intermediate"
    },
    {
        "jungle_id":431506,
        "level":"Intermediate"
    },
    {
        "jungle_id":431508,
        "level":"Intermediate"
    },
    {
        "jungle_id":431509,
        "level":"Intermediate"
    },
    {
        "jungle_id":431510,
        "level":"Advanced"
    },
    {
        "jungle_id":431512,
        "level":"Beginner"
    },
    {
        "jungle_id":431513,
        "level":"Elementary/Pre-Intermediate"
    },
    {
        "jungle_id":431514,
        "level":"Intermediate"
    },
    {
        "jungle_id":431515,
        "level":"Intermediate"
    },
    {
        "jungle_id":431517,
        "level":"Advanced"
    },
    {
        "jungle_id":431520,
        "level":"Text seems to be empty"
    },
    {
        "jungle_id":431521,
        "level":"Upper-Intermediate"
    },
    {
        "jungle_id":431523,
        "level":"Elementary/Pre-Intermediate"
    },
    {
        "jungle_id":431524,
        "level":"Beginner"
    },
    {
        "jungle_id":431526,
        "level":"Upper-Intermediate"
    }
]