[
    {
        "level":"Upper-Intermediate",
        "jungle_id":172108
    },
    {
        "level":"Intermediate",
        "jungle_id":172110
    },
    {
        "level":"Upper-Intermediate",
        "jungle_id":172111
    },
    {
        "level":"Beginner",
        "jungle_id":172112
    },
    {
        "level":"Upper-Intermediate",
        "jungle_id":172115
    },
    {
        "level":"Intermediate",
        "jungle_id":172116
    },
    {
        "level":"Upper-Intermediate",
        "jungle_id":172118
    },
    {
        "level":"Upper-Intermediate",
        "jungle_id":172119
    },
    {
        "level":"Upper-Intermediate",
        "jungle_id":172122
    },
    {
        "level":"Upper-Intermediate",
        "jungle_id":172124
    },
    {
        "level":"Upper-Intermediate",
        "jungle_id":172126
    },
    {
        "level":"Upper-Intermediate",
        "jungle_id":172127
    },
    {
        "level":"Upper-Intermediate",
        "jungle_id":172128
    },
    {
        "level":"Upper-Intermediate",
        "jungle_id":172129
    },
    {
        "level":"Elementary/Pre-Intermediate",
        "jungle_id":172130
    },
    {
        "level":"Upper-Intermediate",
        "jungle_id":172131
    },
    {
        "level":"Upper-Intermediate",
        "jungle_id":172132
    },
    {
        "level":"Upper-Intermediate",
        "jungle_id":172134
    },
    {
        "level":"Upper-Intermediate",
        "jungle_id":172136
    },
    {
        "level":"Upper-Intermediate",
        "jungle_id":172137
    },
    {
        "level":"Upper-Intermediate",
        "jungle_id":172138
    },
    {
        "level":"Upper-Intermediate",
        "jungle_id":172139
    },
    {
        "level":"Upper-Intermediate",
        "jungle_id":172140
    },
    {
        "level":"Upper-Intermediate",
        "jungle_id":172141
    },
    {
        "level":"Upper-Intermediate",
        "jungle_id":172142
    },
    {
        "level":"Upper-Intermediate",
        "jungle_id":172143
    },
    {
        "level":"Advanced",
        "jungle_id":172146
    },
    {
        "level":"Advanced",
        "jungle_id":172148
    },
    {
        "level":"Elementary/Pre-Intermediate",
        "jungle_id":172151
    },
    {
        "level":"Advanced",
        "jungle_id":172152
    }
]