[
    {
        "level":"Upper-Intermediate",
        "jungle_id":188397
    },
    {
        "level":"Intermediate",
        "jungle_id":188398
    },
    {
        "level":"Intermediate",
        "jungle_id":188399
    },
    {
        "level":"Upper-Intermediate",
        "jungle_id":188400
    },
    {
        "level":"Elementary/Pre-Intermediate",
        "jungle_id":188401
    },
    {
        "level":"Upper-Intermediate",
        "jungle_id":188405
    },
    {
        "level":"Upper-Intermediate",
        "jungle_id":188407
    },
    {
        "level":"Upper-Intermediate",
        "jungle_id":188409
    },
    {
        "level":"Upper-Intermediate",
        "jungle_id":188410
    },
    {
        "level":"Elementary/Pre-Intermediate",
        "jungle_id":188411
    },
    {
        "level":"Upper-Intermediate",
        "jungle_id":188412
    },
    {
        "level":"Beginner",
        "jungle_id":188413
    },
    {
        "level":"Elementary/Pre-Intermediate",
        "jungle_id":188415
    },
    {
        "level":"Advanced",
        "jungle_id":188416
    },
    {
        "level":"Upper-Intermediate",
        "jungle_id":188419
    },
    {
        "level":"Upper-Intermediate",
        "jungle_id":188420
    },
    {
        "level":"Intermediate",
        "jungle_id":188422
    },
    {
        "level":"Upper-Intermediate",
        "jungle_id":188423
    },
    {
        "level":"Elementary/Pre-Intermediate",
        "jungle_id":188425
    },
    {
        "level":"Intermediate",
        "jungle_id":188426
    },
    {
        "level":"Upper-Intermediate",
        "jungle_id":188427
    },
    {
        "level":"Upper-Intermediate",
        "jungle_id":188429
    },
    {
        "level":"Intermediate",
        "jungle_id":188430
    },
    {
        "level":"Elementary/Pre-Intermediate",
        "jungle_id":188431
    },
    {
        "level":"Upper-Intermediate",
        "jungle_id":188432
    },
    {
        "level":"Upper-Intermediate",
        "jungle_id":188433
    },
    {
        "level":"Upper-Intermediate",
        "jungle_id":188434
    },
    {
        "level":"Upper-Intermediate",
        "jungle_id":188436
    },
    {
        "level":"Upper-Intermediate",
        "jungle_id":188437
    },
    {
        "level":"Advanced",
        "jungle_id":188438
    },
    {
        "level":"Intermediate",
        "jungle_id":188439
    },
    {
        "level":"Advanced",
        "jungle_id":188440
    },
    {
        "level":"Upper-Intermediate",
        "jungle_id":188441
    },
    {
        "level":"Intermediate",
        "jungle_id":188442
    },
    {
        "level":"Intermediate",
        "jungle_id":188443
    },
    {
        "level":"Elementary/Pre-Intermediate",
        "jungle_id":188445
    },
    {
        "level":"Intermediate",
        "jungle_id":188446
    },
    {
        "level":"Intermediate",
        "jungle_id":188448
    },
    {
        "level":"Upper-Intermediate",
        "jungle_id":188451
    },
    {
        "level":"Upper-Intermediate",
        "jungle_id":188452
    },
    {
        "level":"Elementary/Pre-Intermediate",
        "jungle_id":188453
    },
    {
        "level":"Upper-Intermediate",
        "jungle_id":188455
    }
]