[
    {
        "level":"Upper-Intermediate",
        "jungle_id":227645
    },
    {
        "level":"Elementary/Pre-Intermediate",
        "jungle_id":227648
    },
    {
        "level":"Advanced",
        "jungle_id":227650
    },
    {
        "level":"Advanced",
        "jungle_id":227651
    },
    {
        "level":"Elementary/Pre-Intermediate",
        "jungle_id":227654
    },
    {
        "level":"Intermediate",
        "jungle_id":227655
    },
    {
        "level":"Intermediate",
        "jungle_id":227656
    },
    {
        "level":"Intermediate",
        "jungle_id":227657
    },
    {
        "level":"Intermediate",
        "jungle_id":227658
    },
    {
        "level":"Intermediate",
        "jungle_id":227659
    },
    {
        "level":"Upper-Intermediate",
        "jungle_id":227660
    },
    {
        "level":"Upper-Intermediate",
        "jungle_id":227661
    },
    {
        "level":"Upper-Intermediate",
        "jungle_id":227663
    },
    {
        "level":"Intermediate",
        "jungle_id":227664
    },
    {
        "level":"Advanced",
        "jungle_id":227665
    },
    {
        "level":"Upper-Intermediate",
        "jungle_id":227667
    },
    {
        "level":"Upper-Intermediate",
        "jungle_id":227669
    },
    {
        "level":"Upper-Intermediate",
        "jungle_id":227670
    },
    {
        "level":"Upper-Intermediate",
        "jungle_id":227672
    },
    {
        "level":"Upper-Intermediate",
        "jungle_id":227673
    },
    {
        "level":"Intermediate",
        "jungle_id":227674
    },
    {
        "level":"Intermediate",
        "jungle_id":227675
    },
    {
        "level":"Upper-Intermediate",
        "jungle_id":227676
    },
    {
        "level":"Upper-Intermediate",
        "jungle_id":227677
    },
    {
        "level":"Upper-Intermediate",
        "jungle_id":227680
    },
    {
        "level":"Upper-Intermediate",
        "jungle_id":227682
    },
    {
        "level":"Upper-Intermediate",
        "jungle_id":227684
    },
    {
        "level":"Advanced",
        "jungle_id":227685
    },
    {
        "level":"Elementary/Pre-Intermediate",
        "jungle_id":227686
    },
    {
        "level":"Upper-Intermediate",
        "jungle_id":227689
    },
    {
        "level":"Upper-Intermediate",
        "jungle_id":227690
    },
    {
        "level":"Upper-Intermediate",
        "jungle_id":227691
    },
    {
        "level":"Elementary/Pre-Intermediate",
        "jungle_id":227692
    },
    {
        "level":"Upper-Intermediate",
        "jungle_id":227695
    },
    {
        "level":"Upper-Intermediate",
        "jungle_id":227697
    },
    {
        "level":"Intermediate",
        "jungle_id":227699
    },
    {
        "level":"Upper-Intermediate",
        "jungle_id":227700
    },
    {
        "level":"Advanced",
        "jungle_id":227702
    },
    {
        "level":"Intermediate",
        "jungle_id":227705
    },
    {
        "level":"Advanced",
        "jungle_id":227706
    },
    {
        "level":"Elementary/Pre-Intermediate",
        "jungle_id":227707
    },
    {
        "level":"Intermediate",
        "jungle_id":227708
    },
    {
        "level":"Intermediate",
        "jungle_id":227709
    },
    {
        "level":"Elementary/Pre-Intermediate",
        "jungle_id":227710
    },
    {
        "level":"Advanced",
        "jungle_id":227711
    },
    {
        "level":"Intermediate",
        "jungle_id":227712
    },
    {
        "level":"Elementary/Pre-Intermediate",
        "jungle_id":227714
    },
    {
        "level":"Intermediate",
        "jungle_id":227716
    },
    {
        "level":"Intermediate",
        "jungle_id":227717
    },
    {
        "level":"Intermediate",
        "jungle_id":227719
    },
    {
        "level":"Intermediate",
        "jungle_id":227721
    },
    {
        "level":"Intermediate",
        "jungle_id":227723
    },
    {
        "level":"Intermediate",
        "jungle_id":227724
    },
    {
        "level":"Upper-Intermediate",
        "jungle_id":227726
    }
]