[
    {
        "level":"Advanced",
        "jungle_id":259714
    },
    {
        "level":"Upper-Intermediate",
        "jungle_id":259715
    },
    {
        "level":"Upper-Intermediate",
        "jungle_id":259718
    },
    {
        "level":"Intermediate",
        "jungle_id":259719
    },
    {
        "level":"Intermediate",
        "jungle_id":259720
    },
    {
        "level":"Upper-Intermediate",
        "jungle_id":259721
    },
    {
        "level":"Intermediate",
        "jungle_id":259722
    },
    {
        "level":"Upper-Intermediate",
        "jungle_id":259723
    },
    {
        "level":"Intermediate",
        "jungle_id":259724
    },
    {
        "level":"Intermediate",
        "jungle_id":259725
    },
    {
        "level":"Upper-Intermediate",
        "jungle_id":259726
    },
    {
        "level":"Upper-Intermediate",
        "jungle_id":259727
    },
    {
        "level":"Upper-Intermediate",
        "jungle_id":259728
    }
]