[
    {
        "jungle_id":56747,
        "level":"Upper-Intermediate"
    },
    {
        "jungle_id":56748,
        "level":"Upper-Intermediate"
    },
    {
        "jungle_id":56750,
        "level":"Intermediate"
    },
    {
        "jungle_id":56752,
        "level":"Advanced"
    },
    {
        "jungle_id":56753,
        "level":"Intermediate"
    },
    {
        "jungle_id":56754,
        "level":"Intermediate"
    },
    {
        "jungle_id":56755,
        "level":"Upper-Intermediate"
    },
    {
        "jungle_id":56756,
        "level":"Upper-Intermediate"
    },
    {
        "jungle_id":56757,
        "level":"Elementary/Pre-Intermediate"
    },
    {
        "jungle_id":56758,
        "level":"Intermediate"
    },
    {
        "jungle_id":56759,
        "level":"Elementary/Pre-Intermediate"
    },
    {
        "jungle_id":56760,
        "level":"Elementary/Pre-Intermediate"
    },
    {
        "jungle_id":56761,
        "level":"Advanced"
    },
    {
        "jungle_id":56762,
        "level":"Advanced"
    },
    {
        "jungle_id":56763,
        "level":"Upper-Intermediate"
    },
    {
        "jungle_id":56768,
        "level":"Upper-Intermediate"
    },
    {
        "jungle_id":56769,
        "level":"Upper-Intermediate"
    },
    {
        "jungle_id":56773,
        "level":"Intermediate"
    },
    {
        "jungle_id":56776,
        "level":"Upper-Intermediate"
    },
    {
        "jungle_id":56777,
        "level":"Upper-Intermediate"
    },
    {
        "jungle_id":56778,
        "level":"Upper-Intermediate"
    },
    {
        "jungle_id":56779,
        "level":"Intermediate"
    },
    {
        "jungle_id":56780,
        "level":"Elementary/Pre-Intermediate"
    },
    {
        "jungle_id":56781,
        "level":"Intermediate"
    },
    {
        "jungle_id":56782,
        "level":"Intermediate"
    },
    {
        "jungle_id":56783,
        "level":"Intermediate"
    },
    {
        "jungle_id":56784,
        "level":"Intermediate"
    },
    {
        "jungle_id":56785,
        "level":"Intermediate"
    },
    {
        "jungle_id":56786,
        "level":"Upper-Intermediate"
    },
    {
        "jungle_id":56790,
        "level":"Upper-Intermediate"
    },
    {
        "jungle_id":56792,
        "level":"Elementary/Pre-Intermediate"
    },
    {
        "jungle_id":56794,
        "level":"Elementary/Pre-Intermediate"
    },
    {
        "jungle_id":56795,
        "level":"Advanced"
    },
    {
        "jungle_id":56796,
        "level":"Intermediate"
    },
    {
        "jungle_id":56797,
        "level":"Elementary/Pre-Intermediate"
    },
    {
        "jungle_id":56800,
        "level":"Intermediate"
    },
    {
        "jungle_id":56801,
        "level":"Upper-Intermediate"
    },
    {
        "jungle_id":56803,
        "level":"Advanced"
    },
    {
        "jungle_id":56804,
        "level":"Upper-Intermediate"
    },
    {
        "jungle_id":56805,
        "level":"Intermediate"
    },
    {
        "jungle_id":56809,
        "level":"Intermediate"
    },
    {
        "jungle_id":56810,
        "level":"Upper-Intermediate"
    }
]