[
    {
        "jungle_id":73958,
        "level":"Intermediate"
    },
    {
        "jungle_id":73959,
        "level":"Intermediate"
    },
    {
        "jungle_id":73960,
        "level":"Intermediate"
    },
    {
        "jungle_id":73965,
        "level":"Elementary/Pre-Intermediate"
    },
    {
        "jungle_id":73966,
        "level":"Upper-Intermediate"
    },
    {
        "jungle_id":73967,
        "level":"Upper-Intermediate"
    },
    {
        "jungle_id":73968,
        "level":"Upper-Intermediate"
    },
    {
        "jungle_id":73972,
        "level":"Upper-Intermediate"
    },
    {
        "jungle_id":73973,
        "level":"Beginner"
    },
    {
        "jungle_id":73974,
        "level":"Elementary/Pre-Intermediate"
    },
    {
        "jungle_id":73975,
        "level":"Intermediate"
    },
    {
        "jungle_id":73976,
        "level":"Elementary/Pre-Intermediate"
    },
    {
        "jungle_id":73978,
        "level":"Upper-Intermediate"
    },
    {
        "jungle_id":73979,
        "level":"Upper-Intermediate"
    },
    {
        "jungle_id":73980,
        "level":"Upper-Intermediate"
    },
    {
        "jungle_id":73981,
        "level":"Intermediate"
    },
    {
        "jungle_id":73982,
        "level":"Elementary/Pre-Intermediate"
    },
    {
        "jungle_id":73983,
        "level":"Intermediate"
    },
    {
        "jungle_id":73984,
        "level":"Upper-Intermediate"
    },
    {
        "jungle_id":73985,
        "level":"Upper-Intermediate"
    },
    {
        "jungle_id":73986,
        "level":"Upper-Intermediate"
    },
    {
        "jungle_id":73987,
        "level":"Elementary/Pre-Intermediate"
    },
    {
        "jungle_id":73989,
        "level":"Intermediate"
    },
    {
        "jungle_id":73990,
        "level":"Elementary/Pre-Intermediate"
    },
    {
        "jungle_id":73991,
        "level":"Upper-Intermediate"
    },
    {
        "jungle_id":73992,
        "level":"Upper-Intermediate"
    },
    {
        "jungle_id":73993,
        "level":"Intermediate"
    },
    {
        "jungle_id":73995,
        "level":"Upper-Intermediate"
    },
    {
        "jungle_id":73996,
        "level":"Intermediate"
    },
    {
        "jungle_id":73997,
        "level":"Upper-Intermediate"
    },
    {
        "jungle_id":73998,
        "level":"Intermediate"
    },
    {
        "jungle_id":73999,
        "level":"Upper-Intermediate"
    },
    {
        "jungle_id":74000,
        "level":"Intermediate"
    },
    {
        "jungle_id":74001,
        "level":"Upper-Intermediate"
    },
    {
        "jungle_id":74002,
        "level":"Intermediate"
    },
    {
        "jungle_id":74003,
        "level":"Upper-Intermediate"
    },
    {
        "jungle_id":74005,
        "level":"Elementary/Pre-Intermediate"
    },
    {
        "jungle_id":74006,
        "level":"Intermediate"
    },
    {
        "jungle_id":74007,
        "level":"Elementary/Pre-Intermediate"
    },
    {
        "jungle_id":74008,
        "level":"Advanced"
    },
    {
        "jungle_id":74009,
        "level":"Upper-Intermediate"
    },
    {
        "jungle_id":74010,
        "level":"Intermediate"
    },
    {
        "jungle_id":74011,
        "level":"Elementary/Pre-Intermediate"
    },
    {
        "jungle_id":74012,
        "level":"Upper-Intermediate"
    },
    {
        "jungle_id":74013,
        "level":"Beginner"
    },
    {
        "jungle_id":74015,
        "level":"Upper-Intermediate"
    },
    {
        "jungle_id":74016,
        "level":"Elementary/Pre-Intermediate"
    },
    {
        "jungle_id":74017,
        "level":"Advanced"
    },
    {
        "jungle_id":74018,
        "level":"Upper-Intermediate"
    },
    {
        "jungle_id":74019,
        "level":"Upper-Intermediate"
    },
    {
        "jungle_id":74020,
        "level":"Upper-Intermediate"
    },
    {
        "jungle_id":74021,
        "level":"Upper-Intermediate"
    },
    {
        "jungle_id":74022,
        "level":"Advanced"
    },
    {
        "jungle_id":74023,
        "level":"Beginner"
    },
    {
        "jungle_id":74024,
        "level":"Beginner"
    },
    {
        "jungle_id":74026,
        "level":"Upper-Intermediate"
    }
]