[
    {
        "jungle_id":95571,
        "level":"Upper-Intermediate"
    },
    {
        "jungle_id":95572,
        "level":"Upper-Intermediate"
    },
    {
        "jungle_id":95573,
        "level":"Upper-Intermediate"
    },
    {
        "jungle_id":95574,
        "level":"Upper-Intermediate"
    },
    {
        "jungle_id":95575,
        "level":"Elementary/Pre-Intermediate"
    },
    {
        "jungle_id":95576,
        "level":"Upper-Intermediate"
    },
    {
        "jungle_id":95577,
        "level":"Upper-Intermediate"
    },
    {
        "jungle_id":95578,
        "level":"Upper-Intermediate"
    },
    {
        "jungle_id":95579,
        "level":"Advanced"
    }
]