[
    {
        "jungle_id":97374,
        "level":"Advanced"
    },
    {
        "jungle_id":97375,
        "level":"Intermediate"
    },
    {
        "jungle_id":97378,
        "level":"Intermediate"
    },
    {
        "jungle_id":97380,
        "level":"Intermediate"
    },
    {
        "jungle_id":97383,
        "level":"Elementary/Pre-Intermediate"
    },
    {
        "jungle_id":97384,
        "level":"Intermediate"
    },
    {
        "jungle_id":97385,
        "level":"Intermediate"
    },
    {
        "jungle_id":97387,
        "level":"Intermediate"
    },
    {
        "jungle_id":97389,
        "level":"Advanced"
    },
    {
        "jungle_id":97390,
        "level":"Elementary/Pre-Intermediate"
    },
    {
        "jungle_id":97391,
        "level":"Advanced"
    },
    {
        "jungle_id":97392,
        "level":"Upper-Intermediate"
    },
    {
        "jungle_id":97393,
        "level":"Upper-Intermediate"
    },
    {
        "jungle_id":97394,
        "level":"Intermediate"
    },
    {
        "jungle_id":97395,
        "level":"Elementary/Pre-Intermediate"
    },
    {
        "jungle_id":97396,
        "level":"Intermediate"
    },
    {
        "jungle_id":97397,
        "level":"Advanced"
    },
    {
        "jungle_id":97399,
        "level":"Advanced"
    },
    {
        "jungle_id":97400,
        "level":"Elementary/Pre-Intermediate"
    },
    {
        "jungle_id":97401,
        "level":"Intermediate"
    },
    {
        "jungle_id":97403,
        "level":"Intermediate"
    },
    {
        "jungle_id":97404,
        "level":"Upper-Intermediate"
    },
    {
        "jungle_id":97407,
        "level":"Elementary/Pre-Intermediate"
    },
    {
        "jungle_id":97408,
        "level":"Upper-Intermediate"
    },
    {
        "jungle_id":97409,
        "level":"Intermediate"
    },
    {
        "jungle_id":97410,
        "level":"Intermediate"
    },
    {
        "jungle_id":97411,
        "level":"Intermediate"
    },
    {
        "jungle_id":97412,
        "level":"Advanced"
    },
    {
        "jungle_id":97413,
        "level":"Advanced"
    },
    {
        "jungle_id":97414,
        "level":"Beginner"
    },
    {
        "jungle_id":97416,
        "level":"Upper-Intermediate"
    },
    {
        "jungle_id":97418,
        "level":"Beginner"
    },
    {
        "jungle_id":97419,
        "level":"Intermediate"
    },
    {
        "jungle_id":97421,
        "level":"Upper-Intermediate"
    },
    {
        "jungle_id":97422,
        "level":"Elementary/Pre-Intermediate"
    },
    {
        "jungle_id":97423,
        "level":"Elementary/Pre-Intermediate"
    },
    {
        "jungle_id":97424,
        "level":"Beginner"
    },
    {
        "jungle_id":97425,
        "level":"Elementary/Pre-Intermediate"
    },
    {
        "jungle_id":97426,
        "level":"Intermediate"
    },
    {
        "jungle_id":97427,
        "level":"Upper-Intermediate"
    },
    {
        "jungle_id":97428,
        "level":"Elementary/Pre-Intermediate"
    },
    {
        "jungle_id":97429,
        "level":"Upper-Intermediate"
    },
    {
        "jungle_id":97430,
        "level":"Upper-Intermediate"
    },
    {
        "jungle_id":97431,
        "level":"Advanced"
    },
    {
        "jungle_id":97432,
        "level":"Advanced"
    },
    {
        "jungle_id":97434,
        "level":"Advanced"
    },
    {
        "jungle_id":97436,
        "level":"Advanced"
    },
    {
        "jungle_id":97438,
        "level":"Upper-Intermediate"
    },
    {
        "jungle_id":97439,
        "level":"Advanced"
    },
    {
        "jungle_id":97441,
        "level":"Advanced"
    },
    {
        "jungle_id":97442,
        "level":"Advanced"
    },
    {
        "jungle_id":97443,
        "level":"Advanced"
    },
    {
        "jungle_id":97444,
        "level":"Intermediate"
    },
    {
        "jungle_id":97445,
        "level":"Advanced"
    },
    {
        "jungle_id":97446,
        "level":"Upper-Intermediate"
    },
    {
        "jungle_id":97447,
        "level":"Intermediate"
    },
    {
        "jungle_id":97448,
        "level":"Upper-Intermediate"
    },
    {
        "jungle_id":97449,
        "level":"Intermediate"
    },
    {
        "jungle_id":97451,
        "level":"Intermediate"
    },
    {
        "jungle_id":97453,
        "level":"Intermediate"
    },
    {
        "jungle_id":97454,
        "level":"Intermediate"
    },
    {
        "jungle_id":97455,
        "level":"Advanced"
    },
    {
        "jungle_id":97457,
        "level":"Intermediate"
    },
    {
        "jungle_id":97458,
        "level":"Upper-Intermediate"
    },
    {
        "jungle_id":97459,
        "level":"Upper-Intermediate"
    },
    {
        "jungle_id":97460,
        "level":"Advanced"
    },
    {
        "jungle_id":97461,
        "level":"Advanced"
    },
    {
        "jungle_id":97462,
        "level":"Intermediate"
    },
    {
        "jungle_id":97464,
        "level":"Advanced"
    },
    {
        "jungle_id":97465,
        "level":"Upper-Intermediate"
    },
    {
        "jungle_id":97467,
        "level":"Intermediate"
    },
    {
        "jungle_id":97468,
        "level":"Intermediate"
    },
    {
        "jungle_id":97469,
        "level":"Upper-Intermediate"
    },
    {
        "jungle_id":97470,
        "level":"Intermediate"
    },
    {
        "jungle_id":97471,
        "level":"Elementary/Pre-Intermediate"
    },
    {
        "jungle_id":97472,
        "level":"Intermediate"
    }
]