[
    {
        "jungle_id":126661,
        "level":"Upper-Intermediate"
    },
    {
        "jungle_id":126662,
        "level":"Intermediate"
    },
    {
        "jungle_id":126664,
        "level":"Intermediate"
    },
    {
        "jungle_id":126665,
        "level":"Upper-Intermediate"
    },
    {
        "jungle_id":126667,
        "level":"Beginner"
    },
    {
        "jungle_id":126671,
        "level":"Intermediate"
    },
    {
        "jungle_id":126674,
        "level":"Upper-Intermediate"
    },
    {
        "jungle_id":126675,
        "level":"Upper-Intermediate"
    },
    {
        "jungle_id":126676,
        "level":"Intermediate"
    },
    {
        "jungle_id":126678,
        "level":"Upper-Intermediate"
    },
    {
        "jungle_id":126679,
        "level":"Upper-Intermediate"
    },
    {
        "jungle_id":126680,
        "level":"Elementary/Pre-Intermediate"
    },
    {
        "jungle_id":126683,
        "level":"Elementary/Pre-Intermediate"
    },
    {
        "jungle_id":126684,
        "level":"Advanced"
    },
    {
        "jungle_id":126686,
        "level":"Intermediate"
    },
    {
        "jungle_id":126687,
        "level":"Upper-Intermediate"
    },
    {
        "jungle_id":126688,
        "level":"Elementary/Pre-Intermediate"
    },
    {
        "jungle_id":126689,
        "level":"Intermediate"
    },
    {
        "jungle_id":126690,
        "level":"Upper-Intermediate"
    },
    {
        "jungle_id":126691,
        "level":"Intermediate"
    },
    {
        "jungle_id":126693,
        "level":"Intermediate"
    },
    {
        "jungle_id":126695,
        "level":"Upper-Intermediate"
    },
    {
        "jungle_id":126696,
        "level":"Advanced"
    },
    {
        "jungle_id":126698,
        "level":"Intermediate"
    },
    {
        "jungle_id":126699,
        "level":"Intermediate"
    },
    {
        "jungle_id":126700,
        "level":"Upper-Intermediate"
    },
    {
        "jungle_id":126701,
        "level":"Advanced"
    },
    {
        "jungle_id":126704,
        "level":"Intermediate"
    },
    {
        "jungle_id":126706,
        "level":"Elementary/Pre-Intermediate"
    },
    {
        "jungle_id":126707,
        "level":"Upper-Intermediate"
    },
    {
        "jungle_id":126708,
        "level":"Upper-Intermediate"
    },
    {
        "jungle_id":126709,
        "level":"Elementary/Pre-Intermediate"
    },
    {
        "jungle_id":126710,
        "level":"Upper-Intermediate"
    },
    {
        "jungle_id":126713,
        "level":"Intermediate"
    },
    {
        "jungle_id":126715,
        "level":"Beginner"
    },
    {
        "jungle_id":126716,
        "level":"Advanced"
    },
    {
        "jungle_id":126717,
        "level":"Elementary/Pre-Intermediate"
    },
    {
        "jungle_id":126718,
        "level":"Intermediate"
    },
    {
        "jungle_id":126719,
        "level":"Upper-Intermediate"
    },
    {
        "jungle_id":126720,
        "level":"Intermediate"
    },
    {
        "jungle_id":126721,
        "level":"Intermediate"
    },
    {
        "jungle_id":126722,
        "level":"Intermediate"
    },
    {
        "jungle_id":126723,
        "level":"Upper-Intermediate"
    },
    {
        "jungle_id":126724,
        "level":"Intermediate"
    },
    {
        "jungle_id":126726,
        "level":"Beginner"
    },
    {
        "jungle_id":126727,
        "level":"Upper-Intermediate"
    },
    {
        "jungle_id":126728,
        "level":"Upper-Intermediate"
    },
    {
        "jungle_id":126729,
        "level":"Advanced"
    },
    {
        "jungle_id":126730,
        "level":"Upper-Intermediate"
    },
    {
        "jungle_id":126731,
        "level":"Upper-Intermediate"
    },
    {
        "jungle_id":126733,
        "level":"Intermediate"
    },
    {
        "jungle_id":126734,
        "level":"Upper-Intermediate"
    },
    {
        "jungle_id":126735,
        "level":"Upper-Intermediate"
    },
    {
        "jungle_id":126736,
        "level":"Upper-Intermediate"
    },
    {
        "jungle_id":126737,
        "level":"Upper-Intermediate"
    },
    {
        "jungle_id":126738,
        "level":"Upper-Intermediate"
    }
]